ctor/__init__.py
ctor/common.py
ctor/conversion.py
ctor/errors.py
ctor/py.typed
ctor/typing_utils.py
ctor-0.3.5.dist-info/LICENSE
ctor-0.3.5.dist-info/METADATA
ctor-0.3.5.dist-info/WHEEL
ctor-0.3.5.dist-info/top_level.txt
ctor-0.3.5.dist-info/RECORD
